telebytes/__init__.py
telebytes-1.0.0.dist-info/METADATA
telebytes-1.0.0.dist-info/WHEEL
telebytes-1.0.0.dist-info/top_level.txt
telebytes-1.0.0.dist-info/RECORD
