Metadata-Version: 2.1
Name: telebytes
Version: 1.0.0
Summary: Custom Telethon class for working with session on server.
Author: telebytes
Author-email: nomail@void.io
Requires-Dist: telethon ==1.30.3
Requires-Dist: requests
